WhatsSched/__init__.py
WhatsSched/main.py
WhatsSched-1.0.0.dist-info/LICENSE
WhatsSched-1.0.0.dist-info/METADATA
WhatsSched-1.0.0.dist-info/WHEEL
WhatsSched-1.0.0.dist-info/top_level.txt
WhatsSched-1.0.0.dist-info/RECORD
