Metadata-Version: 2.1
Name: WhatsSched
Version: 1.0.0
Summary: A simple Python module to schedule and send WhatsApp messages at a specific time of your choice.
Home-page: https://github.com/YadavIshant0808/WhatsSched
Author: Ishant Yadav
Author-email: yadav.ishantsbi0985@gmail.com
License: MIT
Classifier: Programming Language :: Python :: 3
Classifier: License :: OSI Approved :: MIT License
Classifier: Operating System :: OS Independent
Requires-Python: >=3.6
License-File: LICENSE
Requires-Dist: pywhatkit
